LICENSE
MANIFEST.in
README.md
setup.py
xontrib/termcolors.py
xontrib_termcolors.egg-info/PKG-INFO
xontrib_termcolors.egg-info/SOURCES.txt
xontrib_termcolors.egg-info/dependency_links.txt
xontrib_termcolors.egg-info/requires.txt
xontrib_termcolors.egg-info/top_level.txt