Metadata-Version: 2.1
Name: xontrib-termcolors
Version: 0.2.0
Summary: Set terminal colors based on selected xonsh theme.
Home-page: https://github.com/dyuri/xontrib-termcolors
Author: Gyuri Horak
Author-email: dyuri@horak.hu
License: MIT
Project-URL: Documentation, https://github.com/dyuri/xontrib-termcolors/blob/master/README.md
Project-URL: Code, https://github.com/dyuri/xontrib-termcolors
Project-URL: Issue tracker, https://github.com/dyuri/xontrib-termcolors/issues
Platform: any
Classifier: Programming Language :: Python :: 3
Classifier: Programming Language :: Python :: 3.6
Classifier: Programming Language :: Python :: 3.7
Classifier: Programming Language :: Python :: 3.8
Classifier: License :: OSI Approved :: MIT License
Classifier: Operating System :: OS Independent
Classifier: Topic :: System :: Shells
Classifier: Topic :: System :: System Shells
Classifier: Topic :: Terminals
Requires-Python: >=3.6
